adafruit_circuitpython_qualia-2.2.1.dist-info/licenses/LICENSE
adafruit_qualia/__init__.py
adafruit_qualia/graphics.py
adafruit_qualia/network.py
adafruit_qualia/peripherals.py
adafruit_qualia/displays/__init__.py
adafruit_qualia/displays/bar240x960.py
adafruit_qualia/displays/bar320x820.py
adafruit_qualia/displays/bar320x960.py
adafruit_qualia/displays/round21.py
adafruit_qualia/displays/round28.py
adafruit_qualia/displays/round40.py
adafruit_qualia/displays/square34.py
adafruit_qualia/displays/square40.py
adafruit_qualia/displays/square40_480x480.py
adafruit_circuitpython_qualia-2.2.1.dist-info/METADATA
adafruit_circuitpython_qualia-2.2.1.dist-info/WHEEL
adafruit_circuitpython_qualia-2.2.1.dist-info/top_level.txt
adafruit_circuitpython_qualia-2.2.1.dist-info/RECORD
