Metadata-Version: 2.4
Name: adafruit-circuitpython-qualia
Version: 2.2.1
Summary: Portal Style Library for the Adafruit Qualia ESP32-S3
Author-email: Adafruit Industries <circuitpython@adafruit.com>
License: MIT
Project-URL: Homepage, https://github.com/adafruit/Adafruit_CircuitPython_Qualia
Keywords: adafruit,blinka,circuitpython,micropython,qualia,qualia,dot,clock,displays,displayio,666,RGB,TTL
Classifier: Intended Audience :: Developers
Classifier: Topic :: Software Development :: Libraries
Classifier: Topic :: Software Development :: Embedded Systems
Classifier: Topic :: System :: Hardware
Classifier: License :: OSI Approved :: MIT License
Classifier: Programming Language :: Python :: 3
License-File: LICENSE
Requires-Dist: Adafruit-Blinka
Requires-Dist: Adafruit-Blinka-displayio
Requires-Dist: adafruit-circuitpython-minimqtt
Requires-Dist: adafruit-circuitpython-miniqr
Requires-Dist: adafruit-circuitpython-requests
Requires-Dist: adafruit-circuitpython-portalbase
Requires-Dist: adafruit-circuitpython-pca9554
Requires-Dist: adafruit-circuitpython-cst8xx
Requires-Dist: adafruit-circuitpython-focaltouch
Provides-Extra: optional
Dynamic: license-file
